{"fighters":[{"name":"Bayonetta","key":"bayonetta"},{"name":"Bowser","key":"koopa"},{"name":"Captain Falcon","key":"captain"},{"name":"Charizard","key":"lizardon"},{"name":"Cloud","key":"cloud"},{"name":"Diddy Kong","key":"diddy"},{"name":"Donkey Kong","key":"donkey"},{"name":"Dr. Mario","key":"mariod"},{"name":"Falco","key":"falco"},{"name":"Fox","key":"fox"},{"name":"Ganondorf","key":"ganon"},{"name":"Greninja","key":"greninja"},{"name":"Ike","key":"ike"},{"name":"Link","key":"link"},{"name":"Little Mac","key":"littlemac"},{"name":"Lucario","key":"lucario"},{"name":"Lucina","key":"lucina"},{"name":"Luigi","key":"luigi"},{"name":"Mario","key":"mario"},{"name":"Marth","key":"marth"},{"name":"Peach","key":"peach"},{"name":"Peach (Cat)","key":"catpeach"},{"name":"Rosalina","key":"rosetta"},{"name":"Rosalina - Luma","key":"tico"},{"name":"Roy","key":"roy"},{"name":"Ryu","key":"ryu"},{"name":"Sheik","key":"sheik"},{"name":"Shulk","key":"shulk"},{"name":"Sonic","key":"sonic"},{"name":"Toon Link","key":"toonlink"},{"name":"Yoshi","key":"yoshi"},{"name":"Zero Suit Samus","key":"szerosuit"}]}